yv_languages/__init__.py
yv_languages/main.py
yv_languages/rules.json
yv_languages/rules.py
yv_languages-1.0.4.dist-info/METADATA
yv_languages-1.0.4.dist-info/WHEEL
yv_languages-1.0.4.dist-info/entry_points.txt
yv_languages-1.0.4.dist-info/top_level.txt
yv_languages-1.0.4.dist-info/RECORD
