Metadata-Version: 2.1
Name: yv-languages
Version: 1.0.4
Summary: Languages package for YouVersion usage.
Home-page: https://gitlab.com/lifechurch/youversion/apis/libraries/yv-languages
Author: Bradley Belyeu
Author-email: bradley.belyeu@youversion.com
Platform: any
Requires-Python: >=3.11.0
Requires-Dist: langcodes
